kin_tokenizer/__init__.py
kin_tokenizer/test_my_code.py
kin_tokenizer/tokenizer.py
kin_tokenizer/utils.py
kin_tokenizer/version.py
kin_tokenizer/data/__init__.py
kin_tokenizer/data/kin_tokenizer.pkl
kin_tokenizer/data/non_kinyarwanda_words.pkl
alta_tokenizer-2.0.dist-info/METADATA
alta_tokenizer-2.0.dist-info/WHEEL
alta_tokenizer-2.0.dist-info/top_level.txt
alta_tokenizer-2.0.dist-info/RECORD
