Metadata-Version: 2.1
Name: alta_tokenizer
Version: 2.0
Summary: ALTA tokenizer for encoding and decoding Kinyarwanda language text
Home-page: https://github.com/Nschadrack/Kin-Tokenizer
Author: Schadrack Niyibizi
Author-email: niyibizischadrack@gmail.com
Keywords: Tokenizer,Kinyarwanda,ALTA Model
Classifier: Programming Language :: Python :: 3
Classifier: Operating System :: OS Independent
Classifier: License :: OSI Approved :: MIT License
Classifier: Intended Audience :: Developers
Classifier: Topic :: Text Processing :: Linguistic
Requires-Python: >=3.12
Requires-Dist: regex >=2024.7.24
Requires-Dist: requests >=2.32.3
